LogAnalyze.py
LogAnalyze-1.0.4.dist-info/License.txt
LogAnalyze-1.0.4.dist-info/METADATA
LogAnalyze-1.0.4.dist-info/WHEEL
LogAnalyze-1.0.4.dist-info/top_level.txt
LogAnalyze-1.0.4.dist-info/RECORD
